edc_list_data/__init__.py
edc_list_data/admin.py
edc_list_data/apps.py
edc_list_data/list_model_maker.py
edc_list_data/load_list_data.py
edc_list_data/load_model_data.py
edc_list_data/model_mixins.py
edc_list_data/models.py
edc_list_data/post_migrate_signals.py
edc_list_data/preload_data.py
edc_list_data/row.py
edc_list_data/site_list_data.py
edc_list_data/stubs.py
edc_list_data/urls.py
edc_list_data/management/commands/__init__.py
edc_list_data/management/commands/load_list_data.py
edc_list_data/migrations/__init__.py
edc_list_data/tests/__init__.py
edc_list_data/tests/admin.py
edc_list_data/tests/list_data.py
edc_list_data/tests/list_data_with_site.py
edc_list_data/tests/models.py
edc_list_data/tests/test_settings.py
edc_list_data/tests/urls.py
edc_list_data/tests/etc/user-aes-local.key
edc_list_data/tests/etc/user-aes-restricted.key
edc_list_data/tests/etc/user-rsa-local-private.pem
edc_list_data/tests/etc/user-rsa-local-public.pem
edc_list_data/tests/etc/user-rsa-restricted-private.pem
edc_list_data/tests/etc/user-rsa-restricted-public.pem
edc_list_data/tests/etc/user-salt-local.key
edc_list_data/tests/etc/user-salt-restricted.key
edc_list_data/tests/tests/__init__.py
edc_list_data/tests/tests/test_preload.py
my_list_app/__init__.py
my_list_app/apps.py
my_list_app/bad_list_data.py
my_list_app/bad_list_data2.py
my_list_app/bad_list_data3.py
my_list_app/dup_list_data.py
my_list_app/list_data.py
my_list_app/model_data.py
my_list_app/model_data2.py
my_list_app/model_data3.py
my_list_app/model_data4.py
edc_list_data-1.0.0.dist-info/AUTHORS
edc_list_data-1.0.0.dist-info/LICENSE
edc_list_data-1.0.0.dist-info/METADATA
edc_list_data-1.0.0.dist-info/WHEEL
edc_list_data-1.0.0.dist-info/top_level.txt
edc_list_data-1.0.0.dist-info/RECORD
